prometheus/__init__.py
prometheus/behavioral_detector.py
prometheus/cli.py
prometheus/engine.py
prometheus/exploit_detector.py
prometheus/models.py
prometheus/signature_engine.py
prometheus/data/intelligence.json
prometheus_community-2.0.0.dist-info/licenses/LICENSE
prometheus_community-2.0.0.dist-info/licenses/NOTICE
prometheus_community-2.0.0.dist-info/METADATA
prometheus_community-2.0.0.dist-info/WHEEL
prometheus_community-2.0.0.dist-info/entry_points.txt
prometheus_community-2.0.0.dist-info/top_level.txt
prometheus_community-2.0.0.dist-info/RECORD
