Metadata-Version: 2.4
Name: prometheus-community
Version: 2.0.0
Summary: The most transparent malware analyzer - Explainable detection with forensic-grade location tracking
Home-page: https://github.com/0x44616D69616E/prometheus-community
Author: Damian Donahue
Author-email: contact@asnspy.com
License: Prometheus Community License v1.0
Project-URL: Bug Tracker, https://github.com/0x44616D69616E/prometheus-community/issues
Project-URL: Documentation, https://github.com/0x44616D69616E/prometheus-community/blob/main/docs
Project-URL: Source Code, https://github.com/0x44616D69616E/prometheus-community
Project-URL: Enterprise Edition, https://github.com/0x44616D69616E/prometheus-enterprise
Project-URL: Discussions, https://github.com/0x44616D69616E/prometheus-community/discussions
Project-URL: Research Paper, https://doi.org/10.5281/zenodo.18123287
Keywords: malware analysis,explainable AI,security,threat intelligence,cybersecurity,reverse engineering,malware detection,behavioral analysis,exploit detection,knowledge graph,security research,forensics,MITRE ATT&CK,transparent detection,location tracking
Classifier: Development Status :: 4 - Beta
Classifier: Intended Audience :: Science/Research
Classifier: Intended Audience :: Education
Classifier: Intended Audience :: Information Technology
Classifier: Intended Audience :: Developers
Classifier: Topic :: Security
Classifier: Topic :: Scientific/Engineering :: Information Analysis
Classifier: Programming Language :: Python :: 3
Classifier: Programming Language :: Python :: 3.8
Classifier: Programming Language :: Python :: 3.9
Classifier: Programming Language :: Python :: 3.10
Classifier: Programming Language :: Python :: 3.11
Classifier: Programming Language :: Python :: 3.12
Classifier: Operating System :: OS Independent
Requires-Python: >=3.8
License-File: LICENSE
License-File: NOTICE
Dynamic: author
Dynamic: author-email
Dynamic: classifier
Dynamic: description
Dynamic: description-content-type
Dynamic: home-page
Dynamic: keywords
Dynamic: license
Dynamic: license-file
Dynamic: project-url
Dynamic: requires-python
Dynamic: summary
